{
  "meta": {
    "title": "幻想乡日报",
    "title_jp": "幻想郷日報",
    "subtitle": "Gensokyo Daily",
    "edition": "第20260305期",
    "updated_at": "2026-03-05T02:10:40.728923+00:00",
    "generated_by": "射命丸文 & GitHub Actions",
    "version": "1.0.0"
  },
  "categories": {
    "official": {
      "label": "头版头条",
      "items": [
        {
          "id": "ff7c674a0c58",
          "title": "2/28(土)～3/15(日)《グランエンタス春祭り2026 with 東方Project》開催！3/6(金)～キュアメイドカフェでのコラボカフェも！",
          "link": "https://touhou-project.news/news/16438/",
          "summary": "今年もグランエンタスに『東方Project』がやってくる！！ 秋葉原オノデン1Fのイベントスペース「グランエンタス」にて、2026年2月28日（土）～3月15日（日）の期間《グランエンタス春祭り2026 with 東方P [&#8230;]",
          "image": null,
          "source": "东方官方资讯站",
          "source_icon": "📰",
          "priority": 1,
          "published": "2026-03-03T10:15:13+00:00",
          "fetched_at": "2026-03-05T02:10:36.873622+00:00"
        },
        {
          "id": "d5b1129f84ee",
          "title": "【東方Project】のオリジナル雑貨とインテリアミニフィギュアを『Can★Do』をはじめとする100円ショップにて発売！",
          "link": "https://touhou-project.news/news/16326/",
          "summary": "株式会社エイコー(本社：東京都墨田区)は、『Can★Do』をはじめとする100円ショップにて【東方Project】のオリジナル商品を発売することをお知らせします。 ■販売商品ラインナップ ・東方Project ゆっくり  [&#8230;]",
          "image": null,
          "source": "东方官方资讯站",
          "source_icon": "📰",
          "priority": 1,
          "published": "2026-03-02T06:17:53+00:00",
          "fetched_at": "2026-03-05T02:10:36.873653+00:00"
        },
        {
          "id": "740c10c0956b",
          "title": "スマホゲーム東方LostWordによる 『LostWord LIVE 2026』がKT Zepp Yokohamaにて開催 3月1日(日)よりチケット一般販売開始",
          "link": "https://touhou-project.news/news/16393/",
          "summary": "株式会社グッドスマイルカンパニーと株式会社NextNinjaの共同プロジェクトである、東方Project公認二次創作スマートフォン向けRPG『東方LostWord（とうほうロストワード）』が5月16日（土）にKT Zep [&#8230;]",
          "image": null,
          "source": "东方官方资讯站",
          "source_icon": "📰",
          "priority": 1,
          "published": "2026-03-02T06:09:19+00:00",
          "fetched_at": "2026-03-05T02:10:36.873676+00:00"
        },
        {
          "id": "4535b9123332",
          "title": "『東方Project』×BOOKOFFコラボ第5弾開催決定！",
          "link": "https://touhou-project.news/news/16403/",
          "summary": "『東方Project』×BOOKOFFコラボ第5弾が3月28日(土)～4月12日(日)まで、ブックオフ対象店舗にて開催いたします！ 第5弾では、人気イラストレーターの夢ノ内氏による「天使界隈」がテーマの描き起こし等身イラ [&#8230;]",
          "image": null,
          "source": "东方官方资讯站",
          "source_icon": "📰",
          "priority": 1,
          "published": "2026-03-02T01:00:54+00:00",
          "fetched_at": "2026-03-05T02:10:36.873697+00:00"
        },
        {
          "id": "bfb2d33ace35",
          "title": "【アキバホビー】東方Project「ゆるっとアクリルキーホルダー」「キャラクターアクリルスタンド」他新作を発売！アキバホビー通販他にて受注開始！",
          "link": "https://touhou-project.news/news/16359/",
          "summary": "株式会社イザナギ（本社：群馬県伊勢崎市　店名：アキバホビー）より、「アクリルキーホルダー ゆるっととうほう」「キャラクターアクリルスタンド」「B2タペストリー」の新商品を発表いたします。 これまでに複数のラインナップをリ [&#8230;]",
          "image": null,
          "source": "东方官方资讯站",
          "source_icon": "📰",
          "priority": 1,
          "published": "2026-02-27T02:01:18+00:00",
          "fetched_at": "2026-03-05T02:10:36.873717+00:00"
        },
        {
          "id": "797279c2a75f",
          "title": "「東方LostWord」最新MV楽曲 東方LostWord feat.シシド・カフカ × 豚乙女による東方アレンジ楽曲「ギラギラGood day」公開！",
          "link": "https://touhou-project.news/news/16340/",
          "summary": "株式会社グッドスマイルカンパニーと株式会社NextNinjaの共同プロジェクトである、東方Project公認二次創作スマートフォン向けRPG『東方LostWord（とうほうロストワード）』が2021年より展開しているMV [&#8230;]",
          "image": null,
          "source": "东方官方资讯站",
          "source_icon": "📰",
          "priority": 1,
          "published": "2026-02-25T04:19:19+00:00",
          "fetched_at": "2026-03-05T02:10:36.873737+00:00"
        },
        {
          "id": "75fd23e526fd",
          "title": "【二次元コスパ】『東方LostWord』博麗霊夢 ＜カルマスピード＞／霧雨魔理沙 ＜夜に裂く光＞各「Tシャツ」が登場！2/28(土)～イベント先行販売も！",
          "link": "https://touhou-project.news/news/16295/",
          "summary": "『東方LostWord』より新グッズ、博麗霊夢 ＜カルマスピード＞／霧雨魔理沙 ＜夜に裂く光＞それぞれの「Tシャツ」が二次元コスパから登場です！ &#160; これらは2月28日(土)～3月15日(日)秋葉原：グランエン [&#8230;]",
          "image": null,
          "source": "东方官方资讯站",
          "source_icon": "📰",
          "priority": 1,
          "published": "2026-02-16T06:06:14+00:00",
          "fetched_at": "2026-03-05T02:10:36.873756+00:00"
        },
        {
          "id": "7a39b9c6b695",
          "title": "「東方Project×平成ギャル in アニメイト」開催決定",
          "link": "https://touhou-project.news/news/16309/",
          "summary": "「東方Project×平成ギャル in アニメイト」が4月18日(土)～5月6日(水)まで、アニメイト対象店舗にて開催いたします！ 柏森たま。氏による「平成ギャル」テーマの描き起こし等身イラストと、京田スズカ氏によるミニ [&#8230;]",
          "image": null,
          "source": "东方官方资讯站",
          "source_icon": "📰",
          "priority": 1,
          "published": "2026-02-16T04:03:20+00:00",
          "fetched_at": "2026-03-05T02:10:36.873787+00:00"
        },
        {
          "id": "38c072f3aa47",
          "title": "「チャイナドレス風衣装」をテーマにした「東方Project」オリジナルグッズが登場！",
          "link": "https://touhou-project.news/news/16274/",
          "summary": "株式会社トキオ・ゲッツより、「チャイナドレス風衣装」をテーマにした「東方Project」博麗霊夢・霧雨魔理沙の新規描き下ろしイラストの新商品が登場します。 &#160; ■予約販売期間■ 2026年2月13日（金）12： [&#8230;]",
          "image": null,
          "source": "东方官方资讯站",
          "source_icon": "📰",
          "priority": 1,
          "published": "2026-02-13T03:00:09+00:00",
          "fetched_at": "2026-03-05T02:10:36.873807+00:00"
        },
        {
          "id": "c900d8665d54",
          "title": "全国のコンビニマルチコピー機で東方Project作品の販売が可能に！FANBOXプリント公認ファンワークス「東方Project」開始",
          "link": "https://touhou-project.news/news/16175/",
          "summary": "2026年2月12日より、FANBOXプリント公認ファンワークス「東方Project」がスタートしました。 これによりFANBOXプリントを通して全国3.3万店舗のコンビニにて、東方Projectのファンアート・マンガが [&#8230;]",
          "image": null,
          "source": "东方官方资讯站",
          "source_icon": "📰",
          "priority": 1,
          "published": "2026-02-12T08:00:17+00:00",
          "fetched_at": "2026-03-05T02:10:36.873825+00:00"
        },
        {
          "id": "8c8fbd8fce64",
          "title": "【Gift】東方ぬいぐるみ（新商品＆再販）通販受付中！",
          "link": "https://touhou-project.news/news/16283/",
          "summary": "東方ぬいぐるみ（新商品＆再販）が「Giftあみあみオンライン出張所」にて通販受付中！（受注生産） ＜受付期間＞ 2026年3月16日（月）23:59頃まで （2026年9月発送予定） 通販ページはコチラ！ ※こちらの商品 [&#8230;]",
          "image": null,
          "source": "东方官方资讯站",
          "source_icon": "📰",
          "priority": 1,
          "published": "2026-02-10T05:05:35+00:00",
          "fetched_at": "2026-03-05T02:10:36.873842+00:00"
        },
        {
          "id": "711e89e43de4",
          "title": "ねんどろいどもあ「ゆっくりしていってね!!!」ご予約受付中！",
          "link": "https://touhou-project.news/news/16180/",
          "summary": "二次創作アスキーアートとしてこの世に生まれ、複雑怪奇な進化を繰り返し、今や動画投稿サイトでその姿を見ない日は無いほど広い世代に浸透した「ゆっくり」が霊夢と魔理沙の２体セットで ねんどろいどもあ シリーズに登場です！ &#038;n [&#8230;]",
          "image": null,
          "source": "东方官方资讯站",
          "source_icon": "📰",
          "priority": 1,
          "published": "2026-02-09T04:00:18+00:00",
          "fetched_at": "2026-03-05T02:10:36.873859+00:00"
        },
        {
          "id": "efdd7ebb5b6e",
          "title": "AKIBAHOBBY將會參加即將在台北舉辦的[2026台北國際動漫節] / 台北で開催される「第14回 台北國際動漫節」にアキバホビーが出展いたします！",
          "link": "https://touhou-project.news/news/16191/",
          "summary": "大家好 我是AKIBAHOBBY宣傳小編 AKIBAHOBBY將會參加於2026年2月5日~2月9日在台北南港展覽館一館舉辦的[第14屆台北國際動漫節] 攤位上將會販售東方PROJECT的官方商品 ・活動概述 ■活動名稱 [&#8230;]",
          "image": null,
          "source": "东方官方资讯站",
          "source_icon": "📰",
          "priority": 1,
          "published": "2026-02-04T11:35:18+00:00",
          "fetched_at": "2026-03-05T02:10:36.873876+00:00"
        },
        {
          "id": "91cd8e5a8e47",
          "title": "AKIBAHOBBY將會參加即將在台北舉辦的[FancyFrontier 46] / 台北で開催される「FancyFrontier 46」にアキバホビーが出展いたします！",
          "link": "https://touhou-project.news/news/16237/",
          "summary": "大家好 我是AKIBAHOBBY宣傳小編 AKIBAHOBBY將會參加於2026年2月6日~2月8日在台北花博公園爭艷館舉辦的[FancyFrontier 46] 攤位上將會販售東方PROJECT的官方商品 ・活動概述  [&#8230;]",
          "image": null,
          "source": "东方官方资讯站",
          "source_icon": "📰",
          "priority": 1,
          "published": "2026-02-04T11:32:07+00:00",
          "fetched_at": "2026-03-05T02:10:36.873892+00:00"
        },
        {
          "id": "c56da52b192a",
          "title": "【フクヤプライズ商品】東方Projectのキャラクターが、　　　　　　　　　　　ぬいぷりけおすわりになって登場！！",
          "link": "https://touhou-project.news/news/16121/",
          "summary": "全国のアミューズメント施設にて東方Projectの「ぬいぷりけおすわり」第１弾～第５弾までが順次展開予定です！ &#160; 「ぬいぷりけおすわり」とは？ &#160; &#160; &#160; “ぬいぷりけ”とは、お [&#8230;]",
          "image": null,
          "source": "东方官方资讯站",
          "source_icon": "📰",
          "priority": 1,
          "published": "2026-01-30T09:00:19+00:00",
          "fetched_at": "2026-03-05T02:10:36.873909+00:00"
        }
      ],
      "count": 15
    },
    "community": {
      "label": "社会·民生",
      "items": [
        {
          "id": "ce438b2454cd",
          "title": "【东方MMD】魂魄妖梦的「このとくべつな音色が素晴らしい」【1440P・镜头配布・歌词】",
          "link": "https://www.bilibili.com/video/BV1vvfiB3EGv",
          "summary": "https://m.youtube.com/watch?v=DqTwbR8Wt4o 作者:8TH 简介:夏服のみょんさんがキノシタさんの「このとくべつな音色が素...",
          "image": "https://i2.hdslb.com/bfs/archive/b50ffcbc86cfec6333909be3e19c9efc491a950d.jpg",
          "source": "B站 MMD榜",
          "source_icon": "💃",
          "priority": 1,
          "published": "2026-03-05T02:00:46+00:00",
          "fetched_at": "2026-03-05T02:10:37.471319+00:00",
          "category": "community"
        },
        {
          "id": "028c968f3f7c",
          "title": "【东方MMD】爱丽丝・玛格特洛依德的ハートアラモード【1440P・镜头配布】",
          "link": "https://www.bilibili.com/video/BV1YzfiBBEwX",
          "summary": "https://m.youtube.com/watch?v=3bf4VPIcfZI 作者:8TH 简介:アリスさんがDECO*27さんのハートアラモードを踊りま...",
          "image": "https://i1.hdslb.com/bfs/archive/451193d2ee72a55dcce409ea4ced93fd81e8d14c.jpg",
          "source": "B站 MMD榜",
          "source_icon": "💃",
          "priority": 1,
          "published": "2026-03-05T02:00:38+00:00",
          "fetched_at": "2026-03-05T02:10:37.471350+00:00",
          "category": "community"
        },
        {
          "id": "8ca9b56301a4",
          "title": "What are they doing?😂",
          "link": "https://www.reddit.com/r/touhou/comments/1rl4eah/what_are_they_doing/",
          "summary": "Every day I see them standing there and I wonder what they are thinking/planning  &#32; submitted by &#32;  /u/Hopeful_Echo9092   [link] &#32; [comments]",
          "image": "https://preview.redd.it/9m0lhppus4ng1.jpeg?width=640&crop=smart&auto=webp&s=8f677b57d1ebd98f4b7c7c503f128980a7c161da",
          "source": "Reddit r/touhou",
          "source_icon": "💬",
          "priority": 2,
          "published": "2026-03-05T01:43:08+00:00",
          "fetched_at": "2026-03-05T02:10:39.814116+00:00"
        },
        {
          "id": "06f3da58dbd3",
          "title": "Hi-no-Kagutsuchi",
          "link": "https://www.reddit.com/r/touhou/comments/1rl4bzu/hinokagutsuchi/",
          "summary": "&#32; submitted by &#32;  /u/Ssr_stardustdiamond   [link] &#32; [comments]",
          "image": "https://preview.redd.it/h27z14i9s4ng1.png?width=640&crop=smart&auto=webp&s=fb2c72f843789076a67750c008bf568773823d0d",
          "source": "Reddit r/touhou",
          "source_icon": "💬",
          "priority": 2,
          "published": "2026-03-05T01:40:09+00:00",
          "fetched_at": "2026-03-05T02:10:39.814148+00:00"
        },
        {
          "id": "02559983ed22",
          "title": "Hey bunny Are you Okey?",
          "link": "https://www.reddit.com/r/touhou/comments/1rl40t1/hey_bunny_are_you_okey/",
          "summary": "normal day on some moons🙂  &#32; submitted by &#32;  /u/Tonka_Triphim   [link] &#32; [comments]",
          "image": "https://preview.redd.it/f96z0egtp4ng1.png?width=320&crop=smart&auto=webp&s=a46f15c7ba1f0c1f1392677f1d239868b140ad80",
          "source": "Reddit r/touhou",
          "source_icon": "💬",
          "priority": 2,
          "published": "2026-03-05T01:26:07+00:00",
          "fetched_at": "2026-03-05T02:10:39.814176+00:00"
        },
        {
          "id": "d9dc9cbeb8ea",
          "title": "Meet the Potential City!!",
          "link": "https://www.reddit.com/r/touhou/comments/1rl3tkt/meet_the_potential_city/",
          "summary": "&#32; submitted by &#32;  /u/Wonderful-Aside-4998   [link] &#32; [comments]",
          "image": "https://preview.redd.it/so7lpg31o4ng1.png?width=640&crop=smart&auto=webp&s=a40d94f5ece3ad1d5d956f6529e7f63ab66c5239",
          "source": "Reddit r/touhou",
          "source_icon": "💬",
          "priority": 2,
          "published": "2026-03-05T01:16:49+00:00",
          "fetched_at": "2026-03-05T02:10:39.814199+00:00"
        },
        {
          "id": "4d616e74f7b4",
          "title": "[Meta] NEW New Horse Year Banner & Icon",
          "link": "https://www.reddit.com/r/touhou/comments/1rl38xo/meta_new_new_horse_year_banner_icon/",
          "summary": "It's a bit late, but we finally got some proper &quot;in-house&quot; art this time, courtesy of /u/LucinaIsMyTank.  &#32; submitted by &#32;  /u/s_reed   [link] &#32; [comments]",
          "image": null,
          "source": "Reddit r/touhou",
          "source_icon": "💬",
          "priority": 2,
          "published": "2026-03-05T00:51:44+00:00",
          "fetched_at": "2026-03-05T02:10:39.814244+00:00"
        },
        {
          "id": "231ae7002bb0",
          "title": "Lawless baka (Video by Cirno's funny and cool channel | Fumolandfill)",
          "link": "https://www.reddit.com/r/touhou/comments/1rl281e/lawless_baka_video_by_cirnos_funny_and_cool/",
          "summary": "&#32; submitted by &#32;  /u/marcopion   [link] &#32; [comments]",
          "image": "https://external-preview.redd.it/AXKtuvBHXeFQZsyG8f9-ud6wlqOCqF533fTDUZGGELE.jpeg?width=320&crop=smart&auto=webp&s=bd544ad8a434e777e08242daa0362e065deae9aa",
          "source": "Reddit r/touhou",
          "source_icon": "💬",
          "priority": 2,
          "published": "2026-03-05T00:07:48+00:00",
          "fetched_at": "2026-03-05T02:10:39.814271+00:00"
        },
        {
          "id": "thwiki_1317689",
          "title": "【百科】Night Floor",
          "link": "https://thwiki.cc/Night%20Floor",
          "summary": "编者: UnknownReposts\n备注: /* Staff */",
          "image": null,
          "source": "THWiki",
          "source_icon": "📚",
          "priority": 2,
          "published": "2026-03-04T23:48:57Z",
          "fetched_at": "2026-03-05T02:10:40.400632+00:00"
        },
        {
          "id": "thwiki_1317688",
          "title": "【百科】Night Floor",
          "link": "https://thwiki.cc/Night%20Floor",
          "summary": "编者: UnknownReposts\n备注: /* 专辑信息 */",
          "image": null,
          "source": "THWiki",
          "source_icon": "📚",
          "priority": 2,
          "published": "2026-03-04T23:34:53Z",
          "fetched_at": "2026-03-05T02:10:40.400654+00:00"
        },
        {
          "id": "thwiki_1317687",
          "title": "【百科】Night Floor",
          "link": "https://thwiki.cc/Night%20Floor",
          "summary": "编者: UnknownReposts\n备注: /* Staff */",
          "image": null,
          "source": "THWiki",
          "source_icon": "📚",
          "priority": 2,
          "published": "2026-03-04T23:34:10Z",
          "fetched_at": "2026-03-05T02:10:40.400662+00:00"
        },
        {
          "id": "thwiki_1317686",
          "title": "【百科】Night Floor",
          "link": "https://thwiki.cc/Night%20Floor",
          "summary": "编者: UnknownReposts\n备注: 无编辑摘要",
          "image": null,
          "source": "THWiki",
          "source_icon": "📚",
          "priority": 2,
          "published": "2026-03-04T23:32:02Z",
          "fetched_at": "2026-03-05T02:10:40.400669+00:00"
        },
        {
          "id": "thwiki_1317685",
          "title": "【百科】十六年の秋",
          "link": "https://thwiki.cc/%E5%8D%81%E5%85%AD%E5%B9%B4%E3%81%AE%E7%A7%8B",
          "summary": "编者: UnknownReposts\n备注: /* 专辑信息 */",
          "image": null,
          "source": "THWiki",
          "source_icon": "📚",
          "priority": 2,
          "published": "2026-03-04T23:23:44Z",
          "fetched_at": "2026-03-05T02:10:40.400686+00:00"
        },
        {
          "id": "thwiki_1317684",
          "title": "【百科】十六年の秋",
          "link": "https://thwiki.cc/%E5%8D%81%E5%85%AD%E5%B9%B4%E3%81%AE%E7%A7%8B",
          "summary": "编者: UnknownReposts\n备注: 无编辑摘要",
          "image": null,
          "source": "THWiki",
          "source_icon": "📚",
          "priority": 2,
          "published": "2026-03-04T23:23:11Z",
          "fetched_at": "2026-03-05T02:10:40.400693+00:00"
        },
        {
          "id": "b58774982804",
          "title": "Hey Touhou community, I need y'alls help.",
          "link": "https://www.reddit.com/r/touhou/comments/1rl0uon/hey_touhou_community_i_need_yalls_help/",
          "summary": "So I'm doing a project about a music artist I've never listened to before. I decided to do Zun because the only Touhou song I've listened to is Bad Apple.  Do you guys have any good recommendations for music from him? Like albums or video game osts? Any recommendations would be greatly appreciated.   &#32; submitted by &#32;  /u/LadyETHNE   [link] &#32; [comments]",
          "image": null,
          "source": "Reddit r/touhou",
          "source_icon": "💬",
          "priority": 2,
          "published": "2026-03-04T23:11:23+00:00",
          "fetched_at": "2026-03-05T02:10:39.814295+00:00"
        },
        {
          "id": "thwiki_1317682",
          "title": "【百科】Lunatic＊＊night party",
          "link": "https://thwiki.cc/Lunatic%EF%BC%8A%EF%BC%8Anight%20party",
          "summary": "编者: UnknownReposts\n备注: /* 曲目列表 */",
          "image": null,
          "source": "THWiki",
          "source_icon": "📚",
          "priority": 2,
          "published": "2026-03-04T23:07:27Z",
          "fetched_at": "2026-03-05T02:10:40.400705+00:00"
        },
        {
          "id": "thwiki_1317681",
          "title": "【百科】Lunatic＊＊night party",
          "link": "https://thwiki.cc/Lunatic%EF%BC%8A%EF%BC%8Anight%20party",
          "summary": "编者: UnknownReposts\n备注: 无编辑摘要",
          "image": null,
          "source": "THWiki",
          "source_icon": "📚",
          "priority": 2,
          "published": "2026-03-04T22:59:42Z",
          "fetched_at": "2026-03-05T02:10:40.400717+00:00"
        },
        {
          "id": "thwiki_1317680",
          "title": "【百科】弐性",
          "link": "https://thwiki.cc/%E5%BC%90%E6%80%A7",
          "summary": "编者: UnknownReposts\n备注: 重定向页面至[[NiSEi]]",
          "image": null,
          "source": "THWiki",
          "source_icon": "📚",
          "priority": 2,
          "published": "2026-03-04T22:55:50Z",
          "fetched_at": "2026-03-05T02:10:40.400726+00:00"
        },
        {
          "id": "bb5cee658e67",
          "title": "Does everyone that loses against reimu becomes part of her “team”?",
          "link": "https://www.reddit.com/r/touhou/comments/1rkzkbm/does_everyone_that_loses_against_reimu_becomes/",
          "summary": "Image source: https://youtu.be/9cu3EqLDE-Y?is=JS1dkctJJHV-PqL6 Like does Remilia or Yuyuko ever try to do another “scheme” to take over or change gensokyo in a “incident”. Or are they “pacified” after defeat and joining Reimus “team” , like in shonen like dragonball with vegeta,bleach with grimmjow?  &#32; submitted by &#32;  /u/Xadlin60   [link] &#32; [comments]",
          "image": "https://preview.redd.it/qkke5heus3ng1.jpeg?width=640&crop=smart&auto=webp&s=cd4673e40eb38c9cda6fefebcaa2dc7245201387",
          "source": "Reddit r/touhou",
          "source_icon": "💬",
          "priority": 2,
          "published": "2026-03-04T22:21:17+00:00",
          "fetched_at": "2026-03-05T02:10:39.814324+00:00"
        },
        {
          "id": "thwiki_1317678",
          "title": "【百科】绯春研究会",
          "link": "https://thwiki.cc/%E7%BB%AF%E6%98%A5%E7%A0%94%E7%A9%B6%E4%BC%9A",
          "summary": "编者: UnknownReposts\n备注: /* 社团信息 */",
          "image": null,
          "source": "THWiki",
          "source_icon": "📚",
          "priority": 2,
          "published": "2026-03-04T21:51:25Z",
          "fetched_at": "2026-03-05T02:10:40.400740+00:00"
        },
        {
          "id": "ceac6a8d3218",
          "title": "A couple more recent drawings, Flandre and Aya!",
          "link": "https://www.reddit.com/r/touhou/comments/1rkxzkr/a_couple_more_recent_drawings_flandre_and_aya/",
          "summary": "&#32; submitted by &#32;  /u/Your-Average-Pull   [link] &#32; [comments]",
          "image": "https://preview.redd.it/st8npg68i3ng1.jpg?width=140&height=112&auto=webp&s=b9712ef50e14cb135c2c5bba2ad28c2fe5df58f6",
          "source": "Reddit r/touhou",
          "source_icon": "💬",
          "priority": 2,
          "published": "2026-03-04T21:21:47+00:00",
          "fetched_at": "2026-03-05T02:10:39.814346+00:00"
        },
        {
          "id": "69e1cf6af2f1",
          "title": "A couple more recent drawings, Flandre and Aya!",
          "link": "https://www.reddit.com/r/touhou/comments/1rkxzgi/a_couple_more_recent_drawings_flandre_and_aya/",
          "summary": "&#32; submitted by &#32;  /u/Your-Average-Pull   [link] &#32; [comments]",
          "image": "https://preview.redd.it/mz856ob7i3ng1.jpg?width=140&height=112&auto=webp&s=b1a34073629db07962f23de7f469b07ac9700d36",
          "source": "Reddit r/touhou",
          "source_icon": "💬",
          "priority": 2,
          "published": "2026-03-04T21:21:39+00:00",
          "fetched_at": "2026-03-05T02:10:39.814368+00:00"
        },
        {
          "id": "11843137ddef",
          "title": "Remilia dynamic test (yo what the heck is going on here😭😭) (by @WhoIsDovi)",
          "link": "https://www.reddit.com/r/touhou/comments/1rkxw8x/remilia_dynamic_test_yo_what_the_heck_is_going_on/",
          "summary": "Source  &#32; submitted by &#32;  /u/Rayskij_Gomes   [link] &#32; [comments]",
          "image": "https://preview.redd.it/5ix6d0lyg3ng1.png?width=640&crop=smart&auto=webp&s=9ecfef7114aad6e8074f577e710fe32d66a5b873",
          "source": "Reddit r/touhou",
          "source_icon": "💬",
          "priority": 2,
          "published": "2026-03-04T21:18:08+00:00",
          "fetched_at": "2026-03-05T02:10:39.814395+00:00"
        },
        {
          "id": "d82b272a693f",
          "title": "Memories of Gensokyo (Touhou Beginnings)",
          "link": "https://www.reddit.com/r/touhou/comments/1rkwp0k/memories_of_gensokyo_touhou_beginnings/",
          "summary": "This is a land forgotten by the confines of man. It mirrors our outside world, but is mystical in nature. Through the eyes of two human children; a shrine maiden and a magician, we see how life can be in Gensokyo. —— Hey, ThatKID here. Been a while. This is my first drawing done on Procreate and it took me a total of 14 HOURS to finish. I’m happy with the result, but I could’ve done some of the stuff a little better. What do you think? One more thing before I leave; I got pre-revisions done, managing to cut the 211 page script into a more digestible 169 page first-draft. I will have a separate post discussing that. The thing you need to know is I cut out or shortened some key moments, while adding things to scenes that felt rushed; on top of doing grammar corrections. Thanks for reading! - ThatKID of Studio Lunar  &#32; submitted by &#32;  /u/Due-Yoghurt-4587   [link] &#32; [comments]",
          "image": "https://preview.redd.it/kjd3fnuh93ng1.jpg?width=140&height=58&auto=webp&s=494395fe756e14e27faef6037d6440cdae7e1572",
          "source": "Reddit r/touhou",
          "source_icon": "💬",
          "priority": 2,
          "published": "2026-03-04T20:32:53+00:00",
          "fetched_at": "2026-03-05T02:10:39.814422+00:00"
        },
        {
          "id": "8c6910670028",
          "title": "War",
          "link": "https://www.reddit.com/r/touhou/comments/1rkwnjq/war/",
          "summary": "&#32; submitted by &#32;  /u/AGE-1EL   [link] &#32; [comments]",
          "image": "https://preview.redd.it/193kytm793ng1.png?width=140&height=99&auto=webp&s=2eb99212f87f1e15ea50bf114aa4679cf9067be7",
          "source": "Reddit r/touhou",
          "source_icon": "💬",
          "priority": 2,
          "published": "2026-03-04T20:31:20+00:00",
          "fetched_at": "2026-03-05T02:10:39.814442+00:00"
        },
        {
          "id": "b9df08a9c964",
          "title": "Momiji",
          "link": "https://www.reddit.com/r/touhou/comments/1rkw2p0/momiji/",
          "summary": "Skeleton meme with Momiji   &#32; submitted by &#32;  /u/KittyGirlArt   [link] &#32; [comments]",
          "image": "https://preview.redd.it/x43zkbqc53ng1.jpeg?width=640&crop=smart&auto=webp&s=d4ae2a95d842596b4c2a5d0495bef25d11d70f74",
          "source": "Reddit r/touhou",
          "source_icon": "💬",
          "priority": 2,
          "published": "2026-03-04T20:09:37+00:00",
          "fetched_at": "2026-03-05T02:10:39.814462+00:00"
        },
        {
          "id": "65be5e9a5bc6",
          "title": "My second deka has arrived! Say hello to Big Baka Cirno",
          "link": "https://www.reddit.com/r/touhou/comments/1rkvyby/my_second_deka_has_arrived_say_hello_to_big_baka/",
          "summary": "&#32; submitted by &#32;  /u/fumosnconsoles   [link] &#32; [comments]",
          "image": null,
          "source": "Reddit r/touhou",
          "source_icon": "💬",
          "priority": 2,
          "published": "2026-03-04T20:05:10+00:00",
          "fetched_at": "2026-03-05T02:10:39.814483+00:00"
        },
        {
          "id": "ae11ffdb4ab9",
          "title": "Touhou AU - Yumeko meets Maribel",
          "link": "https://www.reddit.com/r/touhou/comments/1rkvf0b/touhou_au_yumeko_meets_maribel/",
          "summary": "For context: Yumeko goes to the outside world and meets Maribel Hearn who is the illegitimate child of Yukari and Maribel is unaware of what her mother has done during the invasion of both the Solar and lunar capitals and apologised much to Yumeko's confusion. Maribel: I'm sorry that my mother caused you and your friends grief ! I'm just her illegitimate daughter from Tokyo and I had nothing to do with my mother's schemes or the invasion on your sun capital. I'm just a university student Yumeko: What the hell is up with this kid ? She didn't do anything bad . Hard to believe that she's the bastard daughter of Yukari . She may have inherited her boundary powers but not her cruelty  &#32; submitted by &#32;  /u/Agitated_Orchid_5158   [link] &#32; [comments]",
          "image": "https://preview.redd.it/cstzejmu03ng1.jpeg?width=640&crop=smart&auto=webp&s=16f4a557ad614958e75fae3b0dba59899b1fbb35",
          "source": "Reddit r/touhou",
          "source_icon": "💬",
          "priority": 2,
          "published": "2026-03-04T19:44:54+00:00",
          "fetched_at": "2026-03-05T02:10:39.814508+00:00"
        },
        {
          "id": "c5ae4b50095b",
          "title": "she do be a little prankster...",
          "link": "https://www.reddit.com/r/touhou/comments/1rkuspm/she_do_be_a_little_prankster/",
          "summary": "i don't really know if she chooses the right targets tho... but hey... it's her problem :)   &#32; submitted by &#32;  /u/Interesting-Egg-240   [link] &#32; [comments]",
          "image": "https://preview.redd.it/av45zoanw2ng1.jpg?width=140&height=140&crop=1:1,smart&auto=webp&s=d952e347596235b40bcf37e455b792414d7cd089",
          "source": "Reddit r/touhou",
          "source_icon": "💬",
          "priority": 2,
          "published": "2026-03-04T19:21:38+00:00",
          "fetched_at": "2026-03-05T02:10:39.814531+00:00"
        },
        {
          "id": "8549aafcd57c",
          "title": "Don’t worry she’s used to waking up like this",
          "link": "https://www.reddit.com/r/touhou/comments/1rkuakg/dont_worry_shes_used_to_waking_up_like_this/",
          "summary": "&#32; submitted by &#32;  /u/The_Snoozerz   [link] &#32; [comments]",
          "image": "https://preview.redd.it/1m28jdmgt2ng1.jpeg?width=640&crop=smart&auto=webp&s=721df1753f672d7c4c3a46559f7e58b4ec20c6b3",
          "source": "Reddit r/touhou",
          "source_icon": "💬",
          "priority": 2,
          "published": "2026-03-04T19:02:59+00:00",
          "fetched_at": "2026-03-05T02:10:39.814554+00:00"
        },
        {
          "id": "85fda4813e6d",
          "title": "【直播回放】元宵节快乐！全分段锐评b50 2026年03月04日22点场",
          "link": "https://www.bilibili.com/video/BV1siPizuEzn",
          "summary": "...",
          "image": "https://i2.hdslb.com/bfs/archive/7ef0895c191752f770d684fce1e9db15b59604ba.jpg",
          "source": "B站 游戏榜",
          "source_icon": "🎮",
          "priority": 1,
          "published": "2026-03-04T18:52:56+00:00",
          "fetched_at": "2026-03-04T18:53:45.276401+00:00",
          "category": "community"
        },
        {
          "id": "ce9b6952db6e",
          "title": "Shion's Day Out",
          "link": "https://www.reddit.com/r/touhou/comments/1rktk0x/shions_day_out/",
          "summary": "Joon: &quot;Alright scrot, Yukari is definitely behind this door.&quot; Shion: &quot;Do you promise Joon?&quot; Joon: &quot;Shion, please, I would never lie to you.&quot;  ... Tenshi: &quot;Nice one, that gal is such a loser.&quot; Joon: *in pain* &quot;Oohh, oh my back, oohh..&quot; Tenshi: &quot;So what do you think kid? You wanna get really fucked up?&quot; Shion: &quot;O-okay.&quot; (Based on Luigi's Day Out)  &#32; submitted by &#32;  /u/SatelliteObject87   [link] &#32; [comments]",
          "image": "https://preview.redd.it/b9xr4raro2ng1.jpeg?width=640&crop=smart&auto=webp&s=9813a3fe7bc33d03cb8bdc4a9fe61ea99a212e68",
          "source": "Reddit r/touhou",
          "source_icon": "💬",
          "priority": 2,
          "published": "2026-03-04T18:36:39+00:00",
          "fetched_at": "2026-03-05T02:10:39.814578+00:00"
        },
        {
          "id": "076ad4485fe4",
          "title": "Ordinary Magician",
          "link": "https://www.reddit.com/r/touhou/comments/1rkt2n3/ordinary_magician/",
          "summary": "Follow me! https://www.deviantart.com/tiagothemangaka  &#32; submitted by &#32;  /u/TiagoStormayty   [link] &#32; [comments]",
          "image": "https://preview.redd.it/3u5ac89pl2ng1.jpeg?width=640&crop=smart&auto=webp&s=504fff9b7147f4daef3275e0d1c11d3555e42ce6",
          "source": "Reddit r/touhou",
          "source_icon": "💬",
          "priority": 2,
          "published": "2026-03-04T18:19:36+00:00",
          "fetched_at": "2026-03-05T02:10:39.814599+00:00"
        },
        {
          "id": "2a1ba29faf81",
          "title": "When lw player see main game",
          "link": "https://www.reddit.com/r/touhou/comments/1rksb5f/when_lw_player_see_main_game/",
          "summary": "&#32; submitted by &#32;  /u/IllustriousHurry2380   [link] &#32; [comments]",
          "image": "https://preview.redd.it/3uxegugyg2ng1.jpeg?width=320&crop=smart&auto=webp&s=071dda5c8b5fb893a5a98c965152090aa8ca9b17",
          "source": "Reddit r/touhou",
          "source_icon": "💬",
          "priority": 2,
          "published": "2026-03-04T17:52:53+00:00",
          "fetched_at": "2026-03-05T02:10:39.814619+00:00"
        },
        {
          "id": "thwiki_1317671",
          "title": "【百科】Gensou Hardcore Party Vol.5 -Final-",
          "link": "https://thwiki.cc/Gensou%20Hardcore%20Party%20Vol.5%20-Final-",
          "summary": "编者: UnknownReposts\n备注: 创建页面，内容为“{{同人专辑头部}}  == 专辑信息 == {{同人专辑信息| | 封面 = jpg | 封面角色 = 无 | 名称 = Gensou Hardcore Party Vol.5 -Final- | 制作方 = HaCT&More | 首发日期 = 2026-03-04 | 类型 = 全长 | 风格类型 = 硬核，Trance，其他电子 | 通贩售价 = 1000日元 | 通贩售价补充 =  | 官网页面 = https://x.com/tan5020mint/status/2029173491401146849 | 特定选材 = 东方花映塚 }} {{通贩列表| | 官方 = {{通贩网址…”",
          "image": null,
          "source": "THWiki",
          "source_icon": "📚",
          "priority": 2,
          "published": "2026-03-04T17:42:27Z",
          "fetched_at": "2026-03-04T18:53:46.548819+00:00"
        },
        {
          "id": "thwiki_1317669",
          "title": "【百科】HaCT&More",
          "link": "https://thwiki.cc/HaCT%26More",
          "summary": "编者: UnknownReposts\n备注: /* Gensou Hardcore Party */",
          "image": null,
          "source": "THWiki",
          "source_icon": "📚",
          "priority": 2,
          "published": "2026-03-04T17:23:47Z",
          "fetched_at": "2026-03-04T18:53:46.548847+00:00"
        },
        {
          "id": "6539c72b1a1e",
          "title": "I found Tupai",
          "link": "https://www.reddit.com/r/touhou/comments/1rkr7ei/i_found_tupai/",
          "summary": "&#32; submitted by &#32;  /u/Fresh-Inspector-3537   [link] &#32; [comments]",
          "image": "https://preview.redd.it/6kwsifat92ng1.png?width=640&crop=smart&auto=webp&s=2a92225bd795f35ed7346d5b6493dceeca822a82",
          "source": "Reddit r/touhou",
          "source_icon": "💬",
          "priority": 2,
          "published": "2026-03-04T17:13:00+00:00",
          "fetched_at": "2026-03-05T02:10:39.814639+00:00"
        },
        {
          "id": "84aaca9345b5",
          "title": "Cirno playing on the ice (Gmod)",
          "link": "https://www.reddit.com/r/touhou/comments/1rkqxsm/cirno_playing_on_the_ice_gmod/",
          "summary": "Here's Baka... I mean Cirno playing on the ice. Map: gm_Snowfall, upload by GoldenKnight207, On Garry's Mod Workshop map Character: Miy's Cirno - Touhou Project, upload by CodyVisory73 and 𝚂𝙰𝙺𝚄𝚁𝙴𝙸, on Garry's Mod Workshop Model And don't forget the Character is a character from Touhou Project made by ZUN (Jun'ya Ōta)  &#32; submitted by &#32;  /u/Ledo621_YTB   [link] &#32; [comments]",
          "image": "https://preview.redd.it/zro812cy72ng1.png?width=640&crop=smart&auto=webp&s=2d5c71f809a2678ecf2f3199378489e357f2eae4",
          "source": "Reddit r/touhou",
          "source_icon": "💬",
          "priority": 2,
          "published": "2026-03-04T17:03:13+00:00",
          "fetched_at": "2026-03-05T02:10:39.814664+00:00"
        },
        {
          "id": "c03f16f67ffc",
          "title": "Reimu Hakurei in front of the Shrine (Gmod)",
          "link": "https://www.reddit.com/r/touhou/comments/1rkqwao/reimu_hakurei_in_front_of_the_shrine_gmod/",
          "summary": "Image of Reimu Hakurei from Touhou Project (I haven't played the game, but I know if I do, I'll go crazy.) and (Congratulations to the dedicated Touhou Project player who plays Lunatic) Map: Hakurei shrine (Touhou Maps), Upload by TRIGGER, on Garry's mod Workshop Map  Character: Touhou Project - Hakurei Reimu [schwarz] - Player Model and NPC, upload by 天頂乌 and NanaNana, on Garrys Mod Workshop Model And don't forget the Character are character from Touhou Project made by ZUN (Jun'ya Ōta)  &#32; submitted by &#32;  /u/Ledo621_YTB   [link] &#32; [comments]",
          "image": "https://preview.redd.it/s59bh1ps72ng1.jpg?width=140&height=78&auto=webp&s=1a4e26e8b2373057fa7b19dfef033ce0f152d822",
          "source": "Reddit r/touhou",
          "source_icon": "💬",
          "priority": 2,
          "published": "2026-03-04T17:01:47+00:00",
          "fetched_at": "2026-03-05T02:10:39.814689+00:00"
        },
        {
          "id": "thwiki_1317668",
          "title": "【百科】幻想乡年表",
          "link": "https://thwiki.cc/%E5%B9%BB%E6%83%B3%E4%B9%A1%E5%B9%B4%E8%A1%A8",
          "summary": "编者: 不拘一嗝降人才\n备注: [InPageEdit] /* 问题点 */ 没有编辑摘要",
          "image": null,
          "source": "THWiki",
          "source_icon": "📚",
          "priority": 2,
          "published": "2026-03-04T17:00:33Z",
          "fetched_at": "2026-03-04T18:53:46.548866+00:00"
        },
        {
          "id": "c93309459520",
          "title": "a Patchouli cosplaying a Nepgear, and a Nepgear cosplaying a Patchouli!! because why not, they are both so purple!!",
          "link": "https://www.reddit.com/r/touhou/comments/1rkqueg/a_patchouli_cosplaying_a_nepgear_and_a_nepgear/",
          "summary": "&#32; submitted by &#32;  /u/Rollanan   [link] &#32; [comments]",
          "image": "https://preview.redd.it/6uduesgg72ng1.png?width=640&crop=smart&auto=webp&s=6412ec301978a89690333b1edfdd84a878513744",
          "source": "Reddit r/touhou",
          "source_icon": "💬",
          "priority": 2,
          "published": "2026-03-04T17:00:03+00:00",
          "fetched_at": "2026-03-05T02:10:39.814712+00:00"
        },
        {
          "id": "thwiki_1317666",
          "title": "【百科】幻想郷4コマ旅団 第弐報",
          "link": "https://thwiki.cc/%E5%B9%BB%E6%83%B3%E9%83%B74%E3%82%B3%E3%83%9E%E6%97%85%E5%9B%A3%20%E7%AC%AC%E5%BC%90%E5%A0%B1",
          "summary": "编者: 不拘一嗝降人才\n备注: [InPageEdit] /* Staff */ 没有编辑摘要",
          "image": null,
          "source": "THWiki",
          "source_icon": "📚",
          "priority": 2,
          "published": "2026-03-04T16:54:16Z",
          "fetched_at": "2026-03-04T18:53:46.548887+00:00"
        },
        {
          "id": "thwiki_1317665",
          "title": "【百科】里崎",
          "link": "https://thwiki.cc/%E9%87%8C%E5%B4%8E",
          "summary": "编者: 不拘一嗝降人才\n备注: /* 参与作品 */",
          "image": null,
          "source": "THWiki",
          "source_icon": "📚",
          "priority": 2,
          "published": "2026-03-04T16:51:41Z",
          "fetched_at": "2026-03-04T18:53:46.548896+00:00"
        },
        {
          "id": "thwiki_1317664",
          "title": "【百科】雨山電信",
          "link": "https://thwiki.cc/%E9%9B%A8%E5%B1%B1%E9%9B%BB%E4%BF%A1",
          "summary": "编者: 不拘一嗝降人才\n备注: /* 参与作品 */",
          "image": null,
          "source": "THWiki",
          "source_icon": "📚",
          "priority": 2,
          "published": "2026-03-04T16:51:39Z",
          "fetched_at": "2026-03-04T18:53:46.548904+00:00"
        },
        {
          "id": "thwiki_1317663",
          "title": "【百科】げんずむ",
          "link": "https://thwiki.cc/%E3%81%92%E3%82%93%E3%81%9A%E3%82%80",
          "summary": "编者: 不拘一嗝降人才\n备注: /* 参与作品 */",
          "image": null,
          "source": "THWiki",
          "source_icon": "📚",
          "priority": 2,
          "published": "2026-03-04T16:51:36Z",
          "fetched_at": "2026-03-04T18:53:46.548913+00:00"
        },
        {
          "id": "thwiki_1317662",
          "title": "【百科】公星",
          "link": "https://thwiki.cc/%E5%85%AC%E6%98%9F",
          "summary": "编者: 不拘一嗝降人才\n备注: /* 参与作品 */",
          "image": null,
          "source": "THWiki",
          "source_icon": "📚",
          "priority": 2,
          "published": "2026-03-04T16:51:34Z",
          "fetched_at": "2026-03-04T18:53:46.548925+00:00"
        },
        {
          "id": "thwiki_1317661",
          "title": "【百科】佐藤横丁",
          "link": "https://thwiki.cc/%E4%BD%90%E8%97%A4%E6%A8%AA%E4%B8%81",
          "summary": "编者: 不拘一嗝降人才\n备注: /* 同人志 */",
          "image": null,
          "source": "THWiki",
          "source_icon": "📚",
          "priority": 2,
          "published": "2026-03-04T16:51:02Z",
          "fetched_at": "2026-03-04T18:53:46.548935+00:00"
        },
        {
          "id": "thwiki_1317660",
          "title": "【百科】正木",
          "link": "https://thwiki.cc/%E6%AD%A3%E6%9C%A8",
          "summary": "编者: 不拘一嗝降人才\n备注: /* 参与作品 */",
          "image": null,
          "source": "THWiki",
          "source_icon": "📚",
          "priority": 2,
          "published": "2026-03-04T16:50:50Z",
          "fetched_at": "2026-03-04T18:53:46.548942+00:00"
        },
        {
          "id": "bf5d7f06bb45",
          "title": "Uh.. They go to the moon but they never leave the barrier.... What?? I don't get it.b",
          "link": "https://www.reddit.com/r/touhou/comments/1rkpwiu/uh_they_go_to_the_moon_but_they_never_leave_the/",
          "summary": "Yes I have read SSIB, but if they never leave the barrier then how they get to the moon?? Wild and Horned Hermit ch25  &#32; submitted by &#32;  /u/mmRoo_   [link] &#32; [comments]",
          "image": "https://preview.redd.it/iecmm09912ng1.jpeg?width=640&crop=smart&auto=webp&s=5ac9cfc118857c461365d58341f3390bb29f668e",
          "source": "Reddit r/touhou",
          "source_icon": "💬",
          "priority": 2,
          "published": "2026-03-04T16:25:00+00:00",
          "fetched_at": "2026-03-04T18:53:45.874152+00:00"
        },
        {
          "id": "c1947a4a272c",
          "title": "Deified Human of the Wind ~ Drawing Every Touhou Hisoutensoku character 1/11",
          "link": "https://www.reddit.com/r/touhou/comments/1rkpj45/deified_human_of_the_wind_drawing_every_touhou/",
          "summary": "Drawing Every Touhou Hisoutensoku character 1/11\\ It's strange to be drawing Sanae as my first character of this game, but this is HER game isn't it? Anyway, look at her, ready to fight a giant!\\ Original sprite drawn by alphes for Touhou Hisoutensoku ~ Choudokyuu Ginyoru no Nazo o Oe\\ This art is also on Tumblr, BlueSky, and X/Twitter  &#32; submitted by &#32;  /u/redlerred7   [link] &#32; [comments]",
          "image": "https://preview.redd.it/br0utyfpy1ng1.png?width=640&crop=smart&auto=webp&s=841b1bed954c6bb5e4f62ed1a0ce9841eab712e3",
          "source": "Reddit r/touhou",
          "source_icon": "💬",
          "priority": 2,
          "published": "2026-03-04T16:11:04+00:00",
          "fetched_at": "2026-03-04T18:53:45.874178+00:00"
        }
      ],
      "count": 50
    },
    "art": {
      "label": "艺术·副刊",
      "items": [
        {
          "id": "6526401",
          "title": "Safebooru: 6526401",
          "link": "https://safebooru.org/index.php?page=post&s=view&id=6526401",
          "summary": "Tags: &gt;_&lt; 1girl anzu_cha709 apron bandaid bandaid_...",
          "image": "https://safebooru.org/images/4143/d3412db0b9f21cab403f6bca1e24ec73c1a4ab0d.jpg",
          "source": "Safebooru",
          "source_icon": "🎨",
          "priority": 2,
          "published": "2026-03-05T01:30:08+00:00",
          "fetched_at": "2026-03-05T02:10:40.726289+00:00"
        },
        {
          "id": "6526398",
          "title": "Safebooru: 6526398",
          "link": "https://safebooru.org/index.php?page=post&s=view&id=6526398",
          "summary": "Tags: 1girl ^_^ anzu_cha709 apron arm_ribbon blue_hair b...",
          "image": "https://safebooru.org/images/4143/407625a4ab9de8acd776e6317cf559413c4f53bf.jpg",
          "source": "Safebooru",
          "source_icon": "🎨",
          "priority": 2,
          "published": "2026-03-05T01:30:07+00:00",
          "fetched_at": "2026-03-05T02:10:40.726298+00:00"
        },
        {
          "id": "6526255",
          "title": "Safebooru: 6526255",
          "link": "https://safebooru.org/index.php?page=post&s=view&id=6526255",
          "summary": "Tags: 1girl absurdres blonde_hair blush bush cherry_blos...",
          "image": "https://safebooru.org/images/4143/2506874d697081c19ff77798f4de6d9f531789f1.png",
          "source": "Safebooru",
          "source_icon": "🎨",
          "priority": 2,
          "published": "2026-03-04T23:30:36+00:00",
          "fetched_at": "2026-03-05T02:10:40.726303+00:00"
        },
        {
          "id": "6526242",
          "title": "Safebooru: 6526242",
          "link": "https://safebooru.org/index.php?page=post&s=view&id=6526242",
          "summary": "Tags: 1girl alternate_costume black_shirt bow brown_hair...",
          "image": "https://safebooru.org/images/4143/cb332056999fe0a0f683b3b045e2e9a9f2c8a74a.jpg",
          "source": "Safebooru",
          "source_icon": "🎨",
          "priority": 2,
          "published": "2026-03-04T23:30:30+00:00",
          "fetched_at": "2026-03-05T02:10:40.726308+00:00"
        },
        {
          "id": "6526208",
          "title": "Safebooru: 6526208",
          "link": "https://safebooru.org/index.php?page=post&s=view&id=6526208",
          "summary": "Tags: artist_name credits credits_page email_address gre...",
          "image": "https://safebooru.org/images/4143/eac3ac26886f10fe8221af937c080100a0946cb6.jpg",
          "source": "Safebooru",
          "source_icon": "🎨",
          "priority": 2,
          "published": "2026-03-04T23:30:15+00:00",
          "fetched_at": "2026-03-05T02:10:40.726314+00:00"
        },
        {
          "id": "6526199",
          "title": "Safebooru: 6526199",
          "link": "https://safebooru.org/index.php?page=post&s=view&id=6526199",
          "summary": "Tags: artist_name credits english_text gradient_backgrou...",
          "image": "https://safebooru.org/images/4143/f7d3b979c91842af5f8e82825c160d31c8cf760b.jpg",
          "source": "Safebooru",
          "source_icon": "🎨",
          "priority": 2,
          "published": "2026-03-04T23:30:11+00:00",
          "fetched_at": "2026-03-05T02:10:40.726319+00:00"
        },
        {
          "id": "6526197",
          "title": "Safebooru: 6526197",
          "link": "https://safebooru.org/index.php?page=post&s=view&id=6526197",
          "summary": "Tags: 2girls :d ;d absurdres alternate_hair_color animal...",
          "image": "https://safebooru.org/images/4143/44d400cb240b8ee0890615080617b95e5503561c.jpg",
          "source": "Safebooru",
          "source_icon": "🎨",
          "priority": 2,
          "published": "2026-03-04T23:30:10+00:00",
          "fetched_at": "2026-03-05T02:10:40.726324+00:00"
        },
        {
          "id": "6526139",
          "title": "Safebooru: 6526139",
          "link": "https://safebooru.org/index.php?page=post&s=view&id=6526139",
          "summary": "Tags: 1girl :d ahoge alternate_costume bird_girl bird_wi...",
          "image": "https://safebooru.org/images/4143/7488a050b826f2351e71256eea94e59dabb0594f.jpg",
          "source": "Safebooru",
          "source_icon": "🎨",
          "priority": 2,
          "published": "2026-03-04T23:00:14+00:00",
          "fetched_at": "2026-03-05T02:10:40.726333+00:00"
        },
        {
          "id": "6526051",
          "title": "Safebooru: 6526051",
          "link": "https://safebooru.org/index.php?page=post&s=view&id=6526051",
          "summary": "Tags: 2girls alice_margatroid blonde_hair blue_dress bow...",
          "image": "https://safebooru.org/images/4143/6ec858612f3f5969997cc093595478642cbbe507.png",
          "source": "Safebooru",
          "source_icon": "🎨",
          "priority": 2,
          "published": "2026-03-04T22:00:22+00:00",
          "fetched_at": "2026-03-05T02:10:40.726339+00:00"
        },
        {
          "id": "6526046",
          "title": "Safebooru: 6526046",
          "link": "https://safebooru.org/index.php?page=post&s=view&id=6526046",
          "summary": "Tags: 1girl absurdres alternate_costume belt black_belt ...",
          "image": "https://safebooru.org/images/4143/bc5c4c7ab03146394428ccdbe7bc692217e4445e.png",
          "source": "Safebooru",
          "source_icon": "🎨",
          "priority": 2,
          "published": "2026-03-04T22:00:20+00:00",
          "fetched_at": "2026-03-05T02:10:40.726344+00:00"
        },
        {
          "id": "6526040",
          "title": "Safebooru: 6526040",
          "link": "https://safebooru.org/index.php?page=post&s=view&id=6526040",
          "summary": "Tags: 2girls ? ?? blue_shirt blue_skirt bow breasts brow...",
          "image": "https://safebooru.org/images/4143/d44241bdadbc1745a38c54a84b2d458b91341a73.png",
          "source": "Safebooru",
          "source_icon": "🎨",
          "priority": 2,
          "published": "2026-03-04T22:00:17+00:00",
          "fetched_at": "2026-03-05T02:10:40.726349+00:00"
        },
        {
          "id": "6526037",
          "title": "Safebooru: 6526037",
          "link": "https://safebooru.org/index.php?page=post&s=view&id=6526037",
          "summary": "Tags: 2girls absurdres apron back_bow black_bow black_bo...",
          "image": "https://safebooru.org/images/4143/b105aa3d135f41349da6793aa893003ca8b6c2ac.png",
          "source": "Safebooru",
          "source_icon": "🎨",
          "priority": 2,
          "published": "2026-03-04T22:00:16+00:00",
          "fetched_at": "2026-03-05T02:10:40.726354+00:00"
        },
        {
          "id": "6526000",
          "title": "Safebooru: 6526000",
          "link": "https://safebooru.org/index.php?page=post&s=view&id=6526000",
          "summary": "Tags: 1girl alternate_costume animal_ears black_shoes bl...",
          "image": "https://safebooru.org/images/4143/82f713bc633377139d890517948e452b30acf9de.png",
          "source": "Safebooru",
          "source_icon": "🎨",
          "priority": 2,
          "published": "2026-03-04T21:30:44+00:00",
          "fetched_at": "2026-03-05T02:10:40.726359+00:00"
        },
        {
          "id": "6525997",
          "title": "Safebooru: 6525997",
          "link": "https://safebooru.org/index.php?page=post&s=view&id=6525997",
          "summary": "Tags: 1girl alternate_costume blood blood_on_face bow br...",
          "image": "https://safebooru.org/images/4143/ebff3e0afb1c9cb8293d7355758628bb48759dd6.jpg",
          "source": "Safebooru",
          "source_icon": "🎨",
          "priority": 2,
          "published": "2026-03-04T21:30:43+00:00",
          "fetched_at": "2026-03-05T02:10:40.726364+00:00"
        },
        {
          "id": "6525990",
          "title": "Safebooru: 6525990",
          "link": "https://safebooru.org/index.php?page=post&s=view&id=6525990",
          "summary": "Tags: 1girl absurdres ascot back_bow bat_wings blue_hair...",
          "image": "https://safebooru.org/images/4143/373a2dc42491b9f4ee621b6934dfc10f0cf31066.jpg",
          "source": "Safebooru",
          "source_icon": "🎨",
          "priority": 2,
          "published": "2026-03-04T21:30:41+00:00",
          "fetched_at": "2026-03-05T02:10:40.726369+00:00"
        },
        {
          "id": "6525983",
          "title": "Safebooru: 6525983",
          "link": "https://safebooru.org/index.php?page=post&s=view&id=6525983",
          "summary": "Tags: 1girl absurdres arm_up black_hat black_vest blonde...",
          "image": "https://safebooru.org/images/4143/e45ca83af84b46b685c33b4c4cbbbe90bfbbbfa5.png",
          "source": "Safebooru",
          "source_icon": "🎨",
          "priority": 2,
          "published": "2026-03-04T21:30:36+00:00",
          "fetched_at": "2026-03-05T02:10:40.726376+00:00"
        },
        {
          "id": "6525978",
          "title": "Safebooru: 6525978",
          "link": "https://safebooru.org/index.php?page=post&s=view&id=6525978",
          "summary": "Tags: 1girl artist_name chinese_commentary collared_shir...",
          "image": "https://safebooru.org/images/4143/197ff686537404786130daea53a44019154f8fd5.png",
          "source": "Safebooru",
          "source_icon": "🎨",
          "priority": 2,
          "published": "2026-03-04T21:30:33+00:00",
          "fetched_at": "2026-03-05T02:10:40.726380+00:00"
        },
        {
          "id": "6525969",
          "title": "Safebooru: 6525969",
          "link": "https://safebooru.org/index.php?page=post&s=view&id=6525969",
          "summary": "Tags: 1girl absurdres black_ribbon blue_hat blue_kimono ...",
          "image": "https://safebooru.org/images/4143/94b49c659d74d1e7bd55a1d6dc58d4d6a2b9ad15.png",
          "source": "Safebooru",
          "source_icon": "🎨",
          "priority": 2,
          "published": "2026-03-04T21:30:30+00:00",
          "fetched_at": "2026-03-05T02:10:40.726385+00:00"
        },
        {
          "id": "6525968",
          "title": "Safebooru: 6525968",
          "link": "https://safebooru.org/index.php?page=post&s=view&id=6525968",
          "summary": "Tags: 1girl black_bow black_bowtie black_hairband bow bo...",
          "image": "https://safebooru.org/images/4143/f145e9e2a5a2beaa4a36717def3c426d22b4cda9.jpg",
          "source": "Safebooru",
          "source_icon": "🎨",
          "priority": 2,
          "published": "2026-03-04T21:30:28+00:00",
          "fetched_at": "2026-03-05T02:10:40.726390+00:00"
        },
        {
          "id": "6525965",
          "title": "Safebooru: 6525965",
          "link": "https://safebooru.org/index.php?page=post&s=view&id=6525965",
          "summary": "Tags: 1girl absurdres angel_wings blonde_hair bow bowtie...",
          "image": "https://safebooru.org/images/4143/6404fa7c941beb3068ac641aeefa6e95190118f3.png",
          "source": "Safebooru",
          "source_icon": "🎨",
          "priority": 2,
          "published": "2026-03-04T21:30:27+00:00",
          "fetched_at": "2026-03-05T02:10:40.726395+00:00"
        },
        {
          "id": "6525961",
          "title": "Safebooru: 6525961",
          "link": "https://safebooru.org/index.php?page=post&s=view&id=6525961",
          "summary": "Tags: 2girls absurdres black_bow black_bowtie black_hair...",
          "image": "https://safebooru.org/images/1327/617ecb42be687306e7dbe338316f8d6e93103825.png",
          "source": "Safebooru",
          "source_icon": "🎨",
          "priority": 2,
          "published": "2026-03-04T21:30:26+00:00",
          "fetched_at": "2026-03-05T02:10:40.726400+00:00"
        },
        {
          "id": "6525957",
          "title": "Safebooru: 6525957",
          "link": "https://safebooru.org/index.php?page=post&s=view&id=6525957",
          "summary": "Tags: 1girl absurdres belt black_shoes black_skirt black...",
          "image": "https://safebooru.org/images/1327/107093729592136ebefe78988c22339c4a1ba73b.jpg",
          "source": "Safebooru",
          "source_icon": "🎨",
          "priority": 2,
          "published": "2026-03-04T21:30:25+00:00",
          "fetched_at": "2026-03-05T02:10:40.726405+00:00"
        },
        {
          "id": "6525951",
          "title": "Safebooru: 6525951",
          "link": "https://safebooru.org/index.php?page=post&s=view&id=6525951",
          "summary": "Tags: 1girl absurdres alternate_color ascot back_bow bat...",
          "image": "https://safebooru.org/images/1327/d86c9daa8626809024c534d7b360c631aec4ade6.png",
          "source": "Safebooru",
          "source_icon": "🎨",
          "priority": 2,
          "published": "2026-03-04T21:30:19+00:00",
          "fetched_at": "2026-03-05T02:10:40.726409+00:00"
        },
        {
          "id": "6525943",
          "title": "Safebooru: 6525943",
          "link": "https://safebooru.org/index.php?page=post&s=view&id=6525943",
          "summary": "Tags: 2girls absurdres black_skirt black_vest bleeding b...",
          "image": "https://safebooru.org/images/1327/d07533190f2bfa8e6524aa2753315b82f83b7c45.jpg",
          "source": "Safebooru",
          "source_icon": "🎨",
          "priority": 2,
          "published": "2026-03-04T21:30:16+00:00",
          "fetched_at": "2026-03-05T02:10:40.726416+00:00"
        },
        {
          "id": "6525939",
          "title": "Safebooru: 6525939",
          "link": "https://safebooru.org/index.php?page=post&s=view&id=6525939",
          "summary": "Tags: 2girls absurdres ahoge barefoot black_bow black_bo...",
          "image": "https://safebooru.org/images/1327/9c159508bc924dcdcf5b6269fd03756f845a3ef8.png",
          "source": "Safebooru",
          "source_icon": "🎨",
          "priority": 2,
          "published": "2026-03-04T21:30:13+00:00",
          "fetched_at": "2026-03-05T02:10:40.726421+00:00"
        },
        {
          "id": "6525925",
          "title": "Safebooru: 6525925",
          "link": "https://safebooru.org/index.php?page=post&s=view&id=6525925",
          "summary": "Tags: 3girls black_hat black_pantyhose black_skirt black...",
          "image": "https://safebooru.org/images/1327/b13857003564b86ceaf1c92365c5cd94a3174837.png",
          "source": "Safebooru",
          "source_icon": "🎨",
          "priority": 2,
          "published": "2026-03-04T21:30:08+00:00",
          "fetched_at": "2026-03-05T02:10:40.726425+00:00"
        },
        {
          "id": "6525919",
          "title": "Safebooru: 6525919",
          "link": "https://safebooru.org/index.php?page=post&s=view&id=6525919",
          "summary": "Tags: 3girls ascot blonde_hair blue_eyes blue_skirt brea...",
          "image": "https://safebooru.org/images/1327/2a4a01fe16093437decbbb44a72220e9dcc76a43.png",
          "source": "Safebooru",
          "source_icon": "🎨",
          "priority": 2,
          "published": "2026-03-04T21:30:05+00:00",
          "fetched_at": "2026-03-05T02:10:40.726429+00:00"
        },
        {
          "id": "6525915",
          "title": "Safebooru: 6525915",
          "link": "https://safebooru.org/index.php?page=post&s=view&id=6525915",
          "summary": "Tags: 4girls album_cover_redraw antennae black_necktie b...",
          "image": "https://safebooru.org/images/1327/c2a41e4547b5a0583383f32c11a17004b0cd0093.jpg",
          "source": "Safebooru",
          "source_icon": "🎨",
          "priority": 2,
          "published": "2026-03-04T21:00:35+00:00",
          "fetched_at": "2026-03-05T02:10:40.726433+00:00"
        },
        {
          "id": "6525871",
          "title": "Safebooru: 6525871",
          "link": "https://safebooru.org/index.php?page=post&s=view&id=6525871",
          "summary": "Tags: 1girl absurdres baba_(baba_seimaijo) beads black_b...",
          "image": "https://safebooru.org/images/1327/af8906ddc02a03b256e5cfdbfdbfe461766f3f28.jpg",
          "source": "Safebooru",
          "source_icon": "🎨",
          "priority": 2,
          "published": "2026-03-04T21:00:17+00:00",
          "fetched_at": "2026-03-05T02:10:40.726438+00:00"
        },
        {
          "id": "6525726",
          "title": "Safebooru: 6525726",
          "link": "https://safebooru.org/index.php?page=post&s=view&id=6525726",
          "summary": "Tags: 1girl absurdres ascot black_shoes bow brown_eyes b...",
          "image": "https://safebooru.org/images/1327/985d9b19b43ee614224dbee91ea4699d877e1a2b.png",
          "source": "Safebooru",
          "source_icon": "🎨",
          "priority": 2,
          "published": "2026-03-04T20:00:14+00:00",
          "fetched_at": "2026-03-05T02:10:40.726442+00:00"
        },
        {
          "id": "6525722",
          "title": "Safebooru: 6525722",
          "link": "https://safebooru.org/index.php?page=post&s=view&id=6525722",
          "summary": "Tags: 2girls alternate_costume ascot blush bow brown_hai...",
          "image": "https://safebooru.org/images/1327/4e3246e18a1a21be0ff5da076813f56ac5e7c125.png",
          "source": "Safebooru",
          "source_icon": "🎨",
          "priority": 2,
          "published": "2026-03-04T20:00:11+00:00",
          "fetched_at": "2026-03-05T02:10:40.726447+00:00"
        },
        {
          "id": "6525721",
          "title": "Safebooru: 6525721",
          "link": "https://safebooru.org/index.php?page=post&s=view&id=6525721",
          "summary": "Tags: 2girls alternate_costume ascot blush bow brown_hai...",
          "image": "https://safebooru.org/images/1327/05b98ef041bb19e30da1f140a86f99c3664d3d9b.png",
          "source": "Safebooru",
          "source_icon": "🎨",
          "priority": 2,
          "published": "2026-03-04T20:00:11+00:00",
          "fetched_at": "2026-03-05T02:10:40.726451+00:00"
        },
        {
          "id": "6525710",
          "title": "Safebooru: 6525710",
          "link": "https://safebooru.org/index.php?page=post&s=view&id=6525710",
          "summary": "Tags: 4girls aiming alternate_costume arm_cannon bow chr...",
          "image": "https://safebooru.org/images/1327/9dc94f04d49441ad4a2eafc0963d777b808693af.jpg",
          "source": "Safebooru",
          "source_icon": "🎨",
          "priority": 2,
          "published": "2026-03-04T19:30:29+00:00",
          "fetched_at": "2026-03-05T02:10:40.726455+00:00"
        },
        {
          "id": "6525709",
          "title": "Safebooru: 6525709",
          "link": "https://safebooru.org/index.php?page=post&s=view&id=6525709",
          "summary": "Tags: 4girls aiming alternate_costume animal_costume ant...",
          "image": "https://safebooru.org/images/1327/4a718d53d380b46158c40b082c4bf8e281ce80d5.jpg",
          "source": "Safebooru",
          "source_icon": "🎨",
          "priority": 2,
          "published": "2026-03-04T19:30:29+00:00",
          "fetched_at": "2026-03-05T02:10:40.726460+00:00"
        },
        {
          "id": "6525707",
          "title": "Safebooru: 6525707",
          "link": "https://safebooru.org/index.php?page=post&s=view&id=6525707",
          "summary": "Tags: ! 4girls alternate_costume biting blood bow christ...",
          "image": "https://safebooru.org/images/1327/a02d3125a9009e1c653d778e210bbc011c29751f.jpg",
          "source": "Safebooru",
          "source_icon": "🎨",
          "priority": 2,
          "published": "2026-03-04T19:30:29+00:00",
          "fetched_at": "2026-03-05T02:10:40.726464+00:00"
        },
        {
          "id": "6525706",
          "title": "Safebooru: 6525706",
          "link": "https://safebooru.org/index.php?page=post&s=view&id=6525706",
          "summary": "Tags: 3girls alternate_costume blood bow christmas comme...",
          "image": "https://safebooru.org/images/1327/1d3383eef6b4e65b341afd4891981605f4088b86.jpg",
          "source": "Safebooru",
          "source_icon": "🎨",
          "priority": 2,
          "published": "2026-03-04T19:30:29+00:00",
          "fetched_at": "2026-03-05T02:10:40.726468+00:00"
        },
        {
          "id": "6525705",
          "title": "Safebooru: 6525705",
          "link": "https://safebooru.org/index.php?page=post&s=view&id=6525705",
          "summary": "Tags: ! 4girls alternate_costume blood blush bow christm...",
          "image": "https://safebooru.org/images/1327/c9c3026320a84e3824b9993cc7273050b74b17ff.jpg",
          "source": "Safebooru",
          "source_icon": "🎨",
          "priority": 2,
          "published": "2026-03-04T19:30:29+00:00",
          "fetched_at": "2026-03-05T02:10:40.726472+00:00"
        },
        {
          "id": "6525704",
          "title": "Safebooru: 6525704",
          "link": "https://safebooru.org/index.php?page=post&s=view&id=6525704",
          "summary": "Tags: 4girls alternate_costume animal_costume antlers bl...",
          "image": "https://safebooru.org/images/1327/feafafa4f2ee602c3dce5fc3159c7586d276c612.jpg",
          "source": "Safebooru",
          "source_icon": "🎨",
          "priority": 2,
          "published": "2026-03-04T19:30:28+00:00",
          "fetched_at": "2026-03-05T02:10:40.726479+00:00"
        },
        {
          "id": "6525698",
          "title": "Safebooru: 6525698",
          "link": "https://safebooru.org/index.php?page=post&s=view&id=6525698",
          "summary": "Tags: 1girl alice_margatroid capelet commentary dress gr...",
          "image": "https://safebooru.org/images/1327/1bc43d71f725cf615cae91b819ec7f4a3ffc3712.png",
          "source": "Safebooru",
          "source_icon": "🎨",
          "priority": 2,
          "published": "2026-03-04T19:30:26+00:00",
          "fetched_at": "2026-03-05T02:10:40.726483+00:00"
        },
        {
          "id": "6525696",
          "title": "Safebooru: 6525696",
          "link": "https://safebooru.org/index.php?page=post&s=view&id=6525696",
          "summary": "Tags: 1girl ankle_socks black_bow black_hairband black_s...",
          "image": "https://safebooru.org/images/1327/70386a0b11d22df942979724d96683ba0d847f1a.jpg",
          "source": "Safebooru",
          "source_icon": "🎨",
          "priority": 2,
          "published": "2026-03-04T19:30:26+00:00",
          "fetched_at": "2026-03-05T02:10:40.726486+00:00"
        },
        {
          "id": "6525568",
          "title": "Safebooru: 6525568",
          "link": "https://safebooru.org/index.php?page=post&s=view&id=6525568",
          "summary": "Tags: 1girl @_@ arthropod_girl arthropod_limbs belt blac...",
          "image": "https://safebooru.org/images/1327/0fac2454f8cde5247f99992f4303362d1c05ff72.jpg",
          "source": "Safebooru",
          "source_icon": "🎨",
          "priority": 2,
          "published": "2026-03-04T18:30:11+00:00",
          "fetched_at": "2026-03-04T18:53:47.305403+00:00"
        },
        {
          "id": "6525540",
          "title": "Safebooru: 6525540",
          "link": "https://safebooru.org/index.php?page=post&s=view&id=6525540",
          "summary": "Tags: 1girl artist_name black_dress blonde_hair closed_m...",
          "image": "https://safebooru.org/images/1327/1c4bb64fe393d619dd0de78d9566fbb7e8c48b9e.jpg",
          "source": "Safebooru",
          "source_icon": "🎨",
          "priority": 2,
          "published": "2026-03-04T18:00:37+00:00",
          "fetched_at": "2026-03-04T18:53:47.305411+00:00"
        },
        {
          "id": "6525538",
          "title": "Safebooru: 6525538",
          "link": "https://safebooru.org/index.php?page=post&s=view&id=6525538",
          "summary": "Tags: 1girl absurdres ascot cigarette commentary flandre...",
          "image": "https://safebooru.org/images/1327/b8f72ea867883009a6034152af33e98910061c18.png",
          "source": "Safebooru",
          "source_icon": "🎨",
          "priority": 2,
          "published": "2026-03-04T18:00:36+00:00",
          "fetched_at": "2026-03-04T18:53:47.305417+00:00"
        },
        {
          "id": "6525537",
          "title": "Safebooru: 6525537",
          "link": "https://safebooru.org/index.php?page=post&s=view&id=6525537",
          "summary": "Tags: 1girl absurdres alternate_costume animal_on_lap bl...",
          "image": "https://safebooru.org/images/1327/f70b454c2600b1d2b225849390d3932cdbe36a09.png",
          "source": "Safebooru",
          "source_icon": "🎨",
          "priority": 2,
          "published": "2026-03-04T18:00:35+00:00",
          "fetched_at": "2026-03-04T18:53:47.305422+00:00"
        },
        {
          "id": "6525536",
          "title": "Safebooru: 6525536",
          "link": "https://safebooru.org/index.php?page=post&s=view&id=6525536",
          "summary": "Tags: 3girls :3 animal_ear_fluff animal_ears bare_tree b...",
          "image": "https://safebooru.org/images/1327/7706213b0c638f522cac0bb6870be11285eb0118.png",
          "source": "Safebooru",
          "source_icon": "🎨",
          "priority": 2,
          "published": "2026-03-04T18:00:34+00:00",
          "fetched_at": "2026-03-04T18:53:47.305427+00:00"
        },
        {
          "id": "6525535",
          "title": "Safebooru: 6525535",
          "link": "https://safebooru.org/index.php?page=post&s=view&id=6525535",
          "summary": "Tags: 1girl all_fours black_skirt blue_hat blush broken_...",
          "image": "https://safebooru.org/images/1327/9c17e9189d015a31c04773b09231f9e77aa8a74d.jpg",
          "source": "Safebooru",
          "source_icon": "🎨",
          "priority": 2,
          "published": "2026-03-04T18:00:33+00:00",
          "fetched_at": "2026-03-04T18:53:47.305433+00:00"
        },
        {
          "id": "6525534",
          "title": "Safebooru: 6525534",
          "link": "https://safebooru.org/index.php?page=post&s=view&id=6525534",
          "summary": "Tags: 1girl blue_hat blue_kimono blue_sash blush flower ...",
          "image": "https://safebooru.org/images/1327/973f69ae1609d175022a0e2d97af981b1540e273.jpg",
          "source": "Safebooru",
          "source_icon": "🎨",
          "priority": 2,
          "published": "2026-03-04T18:00:33+00:00",
          "fetched_at": "2026-03-04T18:53:47.305438+00:00"
        },
        {
          "id": "6525533",
          "title": "Safebooru: 6525533",
          "link": "https://safebooru.org/index.php?page=post&s=view&id=6525533",
          "summary": "Tags: 1girl animal_ear_fluff animal_ears braid cat_ears ...",
          "image": "https://safebooru.org/images/1327/559e9c7b68371dd13ac80d0db386fc02d110f7a8.jpg",
          "source": "Safebooru",
          "source_icon": "🎨",
          "priority": 2,
          "published": "2026-03-04T18:00:32+00:00",
          "fetched_at": "2026-03-04T18:53:47.305447+00:00"
        },
        {
          "id": "6525531",
          "title": "Safebooru: 6525531",
          "link": "https://safebooru.org/index.php?page=post&s=view&id=6525531",
          "summary": "Tags: absurdres black_hat city commentary grey_eyes grey...",
          "image": "https://safebooru.org/images/1327/c0f6de2779ddc11123530d4b7890d89d08efbdaf.jpg",
          "source": "Safebooru",
          "source_icon": "🎨",
          "priority": 2,
          "published": "2026-03-04T18:00:31+00:00",
          "fetched_at": "2026-03-04T18:53:47.305453+00:00"
        },
        {
          "id": "6525523",
          "title": "Safebooru: 6525523",
          "link": "https://safebooru.org/index.php?page=post&s=view&id=6525523",
          "summary": "Tags: &gt;_&lt; 1girl black_hat blush closed_eyes conste...",
          "image": "https://safebooru.org/images/1327/91ab72679aff11a864bbd8e4260741532b12f7b9.jpg",
          "source": "Safebooru",
          "source_icon": "🎨",
          "priority": 2,
          "published": "2026-03-04T18:00:28+00:00",
          "fetched_at": "2026-03-04T18:53:47.305458+00:00"
        }
      ],
      "count": 50
    }
  },
  "weather": {
    "updated": "2026-03-05T02:10:40.728900+00:00",
    "forecasts": [
      {
        "location": "博丽神社",
        "location_jp": "博麗神社",
        "condition": "晴",
        "icon": "☀️",
        "temperature": 3
      },
      {
        "location": "人间之里",
        "location_jp": "人間の里",
        "condition": "异变中",
        "icon": "⚡",
        "temperature": 30
      },
      {
        "location": "红魔馆",
        "location_jp": "紅魔館",
        "condition": "雪",
        "icon": "❄️",
        "temperature": 13
      },
      {
        "location": "白玉楼",
        "location_jp": "白玉楼",
        "condition": "弹幕暴风",
        "icon": "🌀",
        "temperature": 4
      },
      {
        "location": "永远亭",
        "location_jp": "永遠亭",
        "condition": "弹幕暴风",
        "icon": "🌀",
        "temperature": 25
      },
      {
        "location": "守矢神社",
        "location_jp": "守矢神社",
        "condition": "异变中",
        "icon": "⚡",
        "temperature": 6
      },
      {
        "location": "地灵殿",
        "location_jp": "地霊殿",
        "condition": "弹幕暴风",
        "icon": "🌀",
        "temperature": 33
      },
      {
        "location": "命莲寺",
        "location_jp": "命蓮寺",
        "condition": "多云",
        "icon": "⛅",
        "temperature": 27
      }
    ]
  },
  "ads": [
    {
      "id": "ad_kappa",
      "title": "河童重工 最新科技",
      "subtitle": "光学迷彩、等离子炮、自动钓鱼机",
      "description": "河城荷取领衔研发！妖怪山河童工业联合体，为您提供最前沿的幻想科技。来料加工、定制弹幕系统，欢迎咨询。",
      "contact": "妖怪山瀑布旁 河童工坊",
      "icon": "🔧"
    },
    {
      "id": "ad_eientei",
      "title": "永远亭 特供药剂",
      "subtitle": "八意永琳监制 · 蓬莱之药除外",
      "description": "感冒灵、跌打丸、弹幕创伤速愈膏……月之头脑为您守护每一天的健康。本月特惠：蝴蝶梦丸（80文/粒）。",
      "contact": "迷途竹林深处 永远亭药局",
      "icon": "💊"
    },
    {
      "id": "ad_kourindou",
      "title": "香霖堂 古道具店",
      "subtitle": "森近霖之助 · 外界道具专营",
      "description": "本店经营各类外界流入品：Game Boy、打火机、不明用途的塑料板……识货的客官请进。不议价。",
      "contact": "魔法森林入口处",
      "icon": "🏪"
    },
    {
      "id": "ad_moriya",
      "title": "守矢神社 御守特卖",
      "subtitle": "信仰充值 · 有求必应",
      "description": "新年限定御守上架！学业成就、恋爱成就、弹幕回避……诹访子大人亲自加持，信仰值翻倍。参拜即送蛙形饼干。",
      "contact": "妖怪山山顶 守矢神社",
      "icon": "⛩️"
    }
  ]
}